scwidgets/__init__.py
scwidgets/_utils.py
scwidgets/css_style.py
scwidgets/check/__init__.py
scwidgets/check/_asserts.py
scwidgets/check/_check.py
scwidgets/check/_widget_check_registry.py
scwidgets/code/__init__.py
scwidgets/code/_widget_code_input.py
scwidgets/code/_widget_parameters_panel.py
scwidgets/css/widgets.css
scwidgets/cue/__init__.py
scwidgets/cue/_widget_cue.py
scwidgets/cue/_widget_cue_box.py
scwidgets/cue/_widget_cue_figure.py
scwidgets/cue/_widget_cue_object.py
scwidgets/cue/_widget_cue_output.py
scwidgets/cue/_widget_reset_cue_button.py
scwidgets/exercise/__init__.py
scwidgets/exercise/_widget_code_exercise.py
scwidgets/exercise/_widget_exercise_registry.py
scwidgets/exercise/_widget_multiplechoice_exercise.py
scwidgets/exercise/_widget_text_exercise.py
scwidgets-0.2.1.dist-info/licenses/LICENSE
scwidgets-0.2.1.dist-info/METADATA
scwidgets-0.2.1.dist-info/WHEEL
scwidgets-0.2.1.dist-info/top_level.txt
scwidgets-0.2.1.dist-info/RECORD
