Metadata-Version: 2.4
Name: scwidgets
Version: 0.2.1
Summary: A collection of widgets to prepare interactive scientific visualisations, including user code input and validation
License: BSD-3-Clause
Project-URL: Documentation, https://scicode-widgets.readthedocs.io/en/latest/
Project-URL: Repository, https://github.com/osscar-org/scicode-widgets
Project-URL: Issues, https://github.com/osscar-org/scicode-widgets/issues
Project-URL: Changelog, https://github.com/osscar-org/scicode-widgets/blob/main/CHANGELOG.md
Classifier: Intended Audience :: Science/Research
Classifier: Operating System :: POSIX
Classifier: License :: OSI Approved :: BSD License
Classifier: Programming Language :: Python
Classifier: Programming Language :: Python :: 3.9
Classifier: Programming Language :: Python :: 3.10
Classifier: Programming Language :: Python :: 3.11
Classifier: Programming Language :: Python :: 3.12
Classifier: Programming Language :: Python :: 3.13
Classifier: Topic :: Scientific/Engineering
Classifier: Topic :: Scientific/Engineering :: Chemistry
Classifier: Topic :: Scientific/Engineering :: Physics
Classifier: Topic :: Software Development :: Libraries :: Python Modules
Requires-Python: >=3.9
License-File: LICENSE
Requires-Dist: ipywidgets>=8.0.0
Requires-Dist: numpy<3.0
Requires-Dist: widget_code_input>=4.0.17
Requires-Dist: matplotlib
Requires-Dist: termcolor
Dynamic: license-file
